{"nodes": [{"id": "c_users_admin_herd_ceit_library_tests_feature_toastnotificationstest_php", "label": "ToastNotificationsTest.php", "file_type": "code", "source_file": "C:\\Users\\admin\\Herd\\CEIT-Library\\tests\\Feature\\ToastNotificationsTest.php", "source_location": "L1"}, {"id": "feature_toastnotificationstest_toastnotificationstest", "label": "ToastNotificationsTest", "file_type": "code", "source_file": "C:\\Users\\admin\\Herd\\CEIT-Library\\tests\\Feature\\ToastNotificationsTest.php", "source_location": "L15"}, {"id": "feature_toastnotificationstest_toastnotificationstest_getroleid", "label": ".getRoleId()", "file_type": "code", "source_file": "C:\\Users\\admin\\Herd\\CEIT-Library\\tests\\Feature\\ToastNotificationsTest.php", "source_location": "L19"}, {"id": "feature_toastnotificationstest_toastnotificationstest_seedrequireddata", "label": ".seedRequiredData()", "file_type": "code", "source_file": "C:\\Users\\admin\\Herd\\CEIT-Library\\tests\\Feature\\ToastNotificationsTest.php", "source_location": "L30"}, {"id": "feature_toastnotificationstest_toastnotificationstest_success_toast_notifications_appear_after_actions", "label": ".success_toast_notifications_appear_after_actions()", "file_type": "code", "source_file": "C:\\Users\\admin\\Herd\\CEIT-Library\\tests\\Feature\\ToastNotificationsTest.php", "source_location": "L44"}, {"id": "feature_toastnotificationstest_toastnotificationstest_error_toast_notifications_appear_on_failures", "label": ".error_toast_notifications_appear_on_failures()", "file_type": "code", "source_file": "C:\\Users\\admin\\Herd\\CEIT-Library\\tests\\Feature\\ToastNotificationsTest.php", "source_location": "L71"}], "edges": [{"source": "c_users_admin_herd_ceit_library_tests_feature_toastnotificationstest_php", "target": "author", "relation": "imports", "context": "import", "confidence": "EXTRACTED", "source_file": "C:\\Users\\admin\\Herd\\CEIT-Library\\tests\\Feature\\ToastNotificationsTest.php", "source_location": "L5", "weight": 1.0}, {"source": "c_users_admin_herd_ceit_library_tests_feature_toastnotificationstest_php", "target": "dean", "relation": "imports", "context": "import", "confidence": "EXTRACTED", "source_file": "C:\\Users\\admin\\Herd\\CEIT-Library\\tests\\Feature\\ToastNotificationsTest.php", "source_location": "L6", "weight": 1.0}, {"source": "c_users_admin_herd_ceit_library_tests_feature_toastnotificationstest_php", "target": "researchadviser", "relation": "imports", "context": "import", "confidence": "EXTRACTED", "source_file": "C:\\Users\\admin\\Herd\\CEIT-Library\\tests\\Feature\\ToastNotificationsTest.php", "source_location": "L7", "weight": 1.0}, {"source": "c_users_admin_herd_ceit_library_tests_feature_toastnotificationstest_php", "target": "role", "relation": "imports", "context": "import", "confidence": "EXTRACTED", "source_file": "C:\\Users\\admin\\Herd\\CEIT-Library\\tests\\Feature\\ToastNotificationsTest.php", "source_location": "L8", "weight": 1.0}, {"source": "c_users_admin_herd_ceit_library_tests_feature_toastnotificationstest_php", "target": "technicaladviser", "relation": "imports", "context": "import", "confidence": "EXTRACTED", "source_file": "C:\\Users\\admin\\Herd\\CEIT-Library\\tests\\Feature\\ToastNotificationsTest.php", "source_location": "L9", "weight": 1.0}, {"source": "c_users_admin_herd_ceit_library_tests_feature_toastnotificationstest_php", "target": "user", "relation": "imports", "context": "import", "confidence": "EXTRACTED", "source_file": "C:\\Users\\admin\\Herd\\CEIT-Library\\tests\\Feature\\ToastNotificationsTest.php", "source_location": "L10", "weight": 1.0}, {"source": "c_users_admin_herd_ceit_library_tests_feature_toastnotificationstest_php", "target": "refreshdatabase", "relation": "imports", "context": "import", "confidence": "EXTRACTED", "source_file": "C:\\Users\\admin\\Herd\\CEIT-Library\\tests\\Feature\\ToastNotificationsTest.php", "source_location": "L11", "weight": 1.0}, {"source": "c_users_admin_herd_ceit_library_tests_feature_toastnotificationstest_php", "target": "volt", "relation": "imports", "context": "import", "confidence": "EXTRACTED", "source_file": "C:\\Users\\admin\\Herd\\CEIT-Library\\tests\\Feature\\ToastNotificationsTest.php", "source_location": "L12", "weight": 1.0}, {"source": "c_users_admin_herd_ceit_library_tests_feature_toastnotificationstest_php", "target": "testcase", "relation": "imports", "context": "import", "confidence": "EXTRACTED", "source_file": "C:\\Users\\admin\\Herd\\CEIT-Library\\tests\\Feature\\ToastNotificationsTest.php", "source_location": "L13", "weight": 1.0}, {"source": "c_users_admin_herd_ceit_library_tests_feature_toastnotificationstest_php", "target": "feature_toastnotificationstest_toastnotificationstest", "relation": "contains", "confidence": "EXTRACTED", "source_file": "C:\\Users\\admin\\Herd\\CEIT-Library\\tests\\Feature\\ToastNotificationsTest.php", "source_location": "L15", "weight": 1.0}, {"source": "feature_toastnotificationstest_toastnotificationstest", "target": "feature_toastnotificationstest_toastnotificationstest_getroleid", "relation": "method", "confidence": "EXTRACTED", "source_file": "C:\\Users\\admin\\Herd\\CEIT-Library\\tests\\Feature\\ToastNotificationsTest.php", "source_location": "L19", "weight": 1.0}, {"source": "feature_toastnotificationstest_toastnotificationstest", "target": "feature_toastnotificationstest_toastnotificationstest_seedrequireddata", "relation": "method", "confidence": "EXTRACTED", "source_file": "C:\\Users\\admin\\Herd\\CEIT-Library\\tests\\Feature\\ToastNotificationsTest.php", "source_location": "L30", "weight": 1.0}, {"source": "feature_toastnotificationstest_toastnotificationstest", "target": "feature_toastnotificationstest_toastnotificationstest_success_toast_notifications_appear_after_actions", "relation": "method", "confidence": "EXTRACTED", "source_file": "C:\\Users\\admin\\Herd\\CEIT-Library\\tests\\Feature\\ToastNotificationsTest.php", "source_location": "L44", "weight": 1.0}, {"source": "feature_toastnotificationstest_toastnotificationstest", "target": "feature_toastnotificationstest_toastnotificationstest_error_toast_notifications_appear_on_failures", "relation": "method", "confidence": "EXTRACTED", "source_file": "C:\\Users\\admin\\Herd\\CEIT-Library\\tests\\Feature\\ToastNotificationsTest.php", "source_location": "L71", "weight": 1.0}, {"source": "feature_toastnotificationstest_toastnotificationstest_success_toast_notifications_appear_after_actions", "target": "feature_toastnotificationstest_toastnotificationstest_seedrequireddata", "relation": "calls", "context": "call", "confidence": "EXTRACTED", "source_file": "C:\\Users\\admin\\Herd\\CEIT-Library\\tests\\Feature\\ToastNotificationsTest.php", "source_location": "L46", "weight": 1.0}, {"source": "feature_toastnotificationstest_toastnotificationstest_success_toast_notifications_appear_after_actions", "target": "feature_toastnotificationstest_toastnotificationstest_getroleid", "relation": "calls", "context": "call", "confidence": "EXTRACTED", "source_file": "C:\\Users\\admin\\Herd\\CEIT-Library\\tests\\Feature\\ToastNotificationsTest.php", "source_location": "L47", "weight": 1.0}, {"source": "feature_toastnotificationstest_toastnotificationstest_error_toast_notifications_appear_on_failures", "target": "feature_toastnotificationstest_toastnotificationstest_seedrequireddata", "relation": "calls", "context": "call", "confidence": "EXTRACTED", "source_file": "C:\\Users\\admin\\Herd\\CEIT-Library\\tests\\Feature\\ToastNotificationsTest.php", "source_location": "L73", "weight": 1.0}, {"source": "feature_toastnotificationstest_toastnotificationstest_error_toast_notifications_appear_on_failures", "target": "feature_toastnotificationstest_toastnotificationstest_getroleid", "relation": "calls", "context": "call", "confidence": "EXTRACTED", "source_file": "C:\\Users\\admin\\Herd\\CEIT-Library\\tests\\Feature\\ToastNotificationsTest.php", "source_location": "L74", "weight": 1.0}], "raw_calls": [{"caller_nid": "feature_toastnotificationstest_toastnotificationstest_getroleid", "callee": "value", "is_member_call": true, "source_file": "C:\\Users\\admin\\Herd\\CEIT-Library\\tests\\Feature\\ToastNotificationsTest.php", "source_location": "L21"}, {"caller_nid": "feature_toastnotificationstest_toastnotificationstest_getroleid", "callee": "Role", "is_member_call": false, "source_file": "C:\\Users\\admin\\Herd\\CEIT-Library\\tests\\Feature\\ToastNotificationsTest.php", "source_location": "L21"}, {"caller_nid": "feature_toastnotificationstest_toastnotificationstest_seedrequireddata", "callee": "Role", "is_member_call": false, "source_file": "C:\\Users\\admin\\Herd\\CEIT-Library\\tests\\Feature\\ToastNotificationsTest.php", "source_location": "L32"}, {"caller_nid": "feature_toastnotificationstest_toastnotificationstest_seedrequireddata", "callee": "Role", "is_member_call": false, "source_file": "C:\\Users\\admin\\Herd\\CEIT-Library\\tests\\Feature\\ToastNotificationsTest.php", "source_location": "L33"}, {"caller_nid": "feature_toastnotificationstest_toastnotificationstest_seedrequireddata", "callee": "Role", "is_member_call": false, "source_file": "C:\\Users\\admin\\Herd\\CEIT-Library\\tests\\Feature\\ToastNotificationsTest.php", "source_location": "L34"}, {"caller_nid": "feature_toastnotificationstest_toastnotificationstest_seedrequireddata", "callee": "Role", "is_member_call": false, "source_file": "C:\\Users\\admin\\Herd\\CEIT-Library\\tests\\Feature\\ToastNotificationsTest.php", "source_location": "L35"}, {"caller_nid": "feature_toastnotificationstest_toastnotificationstest_seedrequireddata", "callee": "create", "is_member_call": true, "source_file": "C:\\Users\\admin\\Herd\\CEIT-Library\\tests\\Feature\\ToastNotificationsTest.php", "source_location": "L37"}, {"caller_nid": "feature_toastnotificationstest_toastnotificationstest_seedrequireddata", "callee": "count", "is_member_call": true, "source_file": "C:\\Users\\admin\\Herd\\CEIT-Library\\tests\\Feature\\ToastNotificationsTest.php", "source_location": "L37"}, {"caller_nid": "feature_toastnotificationstest_toastnotificationstest_seedrequireddata", "callee": "ResearchAdviser", "is_member_call": false, "source_file": "C:\\Users\\admin\\Herd\\CEIT-Library\\tests\\Feature\\ToastNotificationsTest.php", "source_location": "L37"}, {"caller_nid": "feature_toastnotificationstest_toastnotificationstest_seedrequireddata", "callee": "create", "is_member_call": true, "source_file": "C:\\Users\\admin\\Herd\\CEIT-Library\\tests\\Feature\\ToastNotificationsTest.php", "source_location": "L38"}, {"caller_nid": "feature_toastnotificationstest_toastnotificationstest_seedrequireddata", "callee": "count", "is_member_call": true, "source_file": "C:\\Users\\admin\\Herd\\CEIT-Library\\tests\\Feature\\ToastNotificationsTest.php", "source_location": "L38"}, {"caller_nid": "feature_toastnotificationstest_toastnotificationstest_seedrequireddata", "callee": "TechnicalAdviser", "is_member_call": false, "source_file": "C:\\Users\\admin\\Herd\\CEIT-Library\\tests\\Feature\\ToastNotificationsTest.php", "source_location": "L38"}, {"caller_nid": "feature_toastnotificationstest_toastnotificationstest_seedrequireddata", "callee": "create", "is_member_call": true, "source_file": "C:\\Users\\admin\\Herd\\CEIT-Library\\tests\\Feature\\ToastNotificationsTest.php", "source_location": "L39"}, {"caller_nid": "feature_toastnotificationstest_toastnotificationstest_seedrequireddata", "callee": "count", "is_member_call": true, "source_file": "C:\\Users\\admin\\Herd\\CEIT-Library\\tests\\Feature\\ToastNotificationsTest.php", "source_location": "L39"}, {"caller_nid": "feature_toastnotificationstest_toastnotificationstest_seedrequireddata", "callee": "Dean", "is_member_call": false, "source_file": "C:\\Users\\admin\\Herd\\CEIT-Library\\tests\\Feature\\ToastNotificationsTest.php", "source_location": "L39"}, {"caller_nid": "feature_toastnotificationstest_toastnotificationstest_seedrequireddata", "callee": "create", "is_member_call": true, "source_file": "C:\\Users\\admin\\Herd\\CEIT-Library\\tests\\Feature\\ToastNotificationsTest.php", "source_location": "L40"}, {"caller_nid": "feature_toastnotificationstest_toastnotificationstest_seedrequireddata", "callee": "count", "is_member_call": true, "source_file": "C:\\Users\\admin\\Herd\\CEIT-Library\\tests\\Feature\\ToastNotificationsTest.php", "source_location": "L40"}, {"caller_nid": "feature_toastnotificationstest_toastnotificationstest_seedrequireddata", "callee": "Author", "is_member_call": false, "source_file": "C:\\Users\\admin\\Herd\\CEIT-Library\\tests\\Feature\\ToastNotificationsTest.php", "source_location": "L40"}, {"caller_nid": "feature_toastnotificationstest_toastnotificationstest_success_toast_notifications_appear_after_actions", "callee": "create", "is_member_call": true, "source_file": "C:\\Users\\admin\\Herd\\CEIT-Library\\tests\\Feature\\ToastNotificationsTest.php", "source_location": "L47"}, {"caller_nid": "feature_toastnotificationstest_toastnotificationstest_success_toast_notifications_appear_after_actions", "callee": "User", "is_member_call": false, "source_file": "C:\\Users\\admin\\Herd\\CEIT-Library\\tests\\Feature\\ToastNotificationsTest.php", "source_location": "L47"}, {"caller_nid": "feature_toastnotificationstest_toastnotificationstest_success_toast_notifications_appear_after_actions", "callee": "actingAs", "is_member_call": true, "source_file": "C:\\Users\\admin\\Herd\\CEIT-Library\\tests\\Feature\\ToastNotificationsTest.php", "source_location": "L48"}, {"caller_nid": "feature_toastnotificationstest_toastnotificationstest_success_toast_notifications_appear_after_actions", "callee": "toArray", "is_member_call": true, "source_file": "C:\\Users\\admin\\Herd\\CEIT-Library\\tests\\Feature\\ToastNotificationsTest.php", "source_location": "L50"}, {"caller_nid": "feature_toastnotificationstest_toastnotificationstest_success_toast_notifications_appear_after_actions", "callee": "make", "is_member_call": true, "source_file": "C:\\Users\\admin\\Herd\\CEIT-Library\\tests\\Feature\\ToastNotificationsTest.php", "source_location": "L50"}, {"caller_nid": "feature_toastnotificationstest_toastnotificationstest_success_toast_notifications_appear_after_actions", "callee": "AcademicPaper", "is_member_call": false, "source_file": "C:\\Users\\admin\\Herd\\CEIT-Library\\tests\\Feature\\ToastNotificationsTest.php", "source_location": "L50"}, {"caller_nid": "feature_toastnotificationstest_toastnotificationstest_success_toast_notifications_appear_after_actions", "callee": "toArray", "is_member_call": true, "source_file": "C:\\Users\\admin\\Herd\\CEIT-Library\\tests\\Feature\\ToastNotificationsTest.php", "source_location": "L51"}, {"caller_nid": "feature_toastnotificationstest_toastnotificationstest_success_toast_notifications_appear_after_actions", "callee": "pluck", "is_member_call": true, "source_file": "C:\\Users\\admin\\Herd\\CEIT-Library\\tests\\Feature\\ToastNotificationsTest.php", "source_location": "L51"}, {"caller_nid": "feature_toastnotificationstest_toastnotificationstest_success_toast_notifications_appear_after_actions", "callee": "limit", "is_member_call": true, "source_file": "C:\\Users\\admin\\Herd\\CEIT-Library\\tests\\Feature\\ToastNotificationsTest.php", "source_location": "L51"}, {"caller_nid": "feature_toastnotificationstest_toastnotificationstest_success_toast_notifications_appear_after_actions", "callee": "Author", "is_member_call": false, "source_file": "C:\\Users\\admin\\Herd\\CEIT-Library\\tests\\Feature\\ToastNotificationsTest.php", "source_location": "L51"}, {"caller_nid": "feature_toastnotificationstest_toastnotificationstest_success_toast_notifications_appear_after_actions", "callee": "set", "is_member_call": true, "source_file": "C:\\Users\\admin\\Herd\\CEIT-Library\\tests\\Feature\\ToastNotificationsTest.php", "source_location": "L53"}, {"caller_nid": "feature_toastnotificationstest_toastnotificationstest_success_toast_notifications_appear_after_actions", "callee": "set", "is_member_call": true, "source_file": "C:\\Users\\admin\\Herd\\CEIT-Library\\tests\\Feature\\ToastNotificationsTest.php", "source_location": "L53"}, {"caller_nid": "feature_toastnotificationstest_toastnotificationstest_success_toast_notifications_appear_after_actions", "callee": "set", "is_member_call": true, "source_file": "C:\\Users\\admin\\Herd\\CEIT-Library\\tests\\Feature\\ToastNotificationsTest.php", "source_location": "L53"}, {"caller_nid": "feature_toastnotificationstest_toastnotificationstest_success_toast_notifications_appear_after_actions", "callee": "set", "is_member_call": true, "source_file": "C:\\Users\\admin\\Herd\\CEIT-Library\\tests\\Feature\\ToastNotificationsTest.php", "source_location": "L53"}, {"caller_nid": "feature_toastnotificationstest_toastnotificationstest_success_toast_notifications_appear_after_actions", "callee": "set", "is_member_call": true, "source_file": "C:\\Users\\admin\\Herd\\CEIT-Library\\tests\\Feature\\ToastNotificationsTest.php", "source_location": "L53"}, {"caller_nid": "feature_toastnotificationstest_toastnotificationstest_success_toast_notifications_appear_after_actions", "callee": "set", "is_member_call": true, "source_file": "C:\\Users\\admin\\Herd\\CEIT-Library\\tests\\Feature\\ToastNotificationsTest.php", "source_location": "L53"}, {"caller_nid": "feature_toastnotificationstest_toastnotificationstest_success_toast_notifications_appear_after_actions", "callee": "set", "is_member_call": true, "source_file": "C:\\Users\\admin\\Herd\\CEIT-Library\\tests\\Feature\\ToastNotificationsTest.php", "source_location": "L53"}, {"caller_nid": "feature_toastnotificationstest_toastnotificationstest_success_toast_notifications_appear_after_actions", "callee": "set", "is_member_call": true, "source_file": "C:\\Users\\admin\\Herd\\CEIT-Library\\tests\\Feature\\ToastNotificationsTest.php", "source_location": "L53"}, {"caller_nid": "feature_toastnotificationstest_toastnotificationstest_success_toast_notifications_appear_after_actions", "callee": "set", "is_member_call": true, "source_file": "C:\\Users\\admin\\Herd\\CEIT-Library\\tests\\Feature\\ToastNotificationsTest.php", "source_location": "L53"}, {"caller_nid": "feature_toastnotificationstest_toastnotificationstest_success_toast_notifications_appear_after_actions", "callee": "Volt", "is_member_call": false, "source_file": "C:\\Users\\admin\\Herd\\CEIT-Library\\tests\\Feature\\ToastNotificationsTest.php", "source_location": "L53"}, {"caller_nid": "feature_toastnotificationstest_toastnotificationstest_success_toast_notifications_appear_after_actions", "callee": "ResearchAdviser", "is_member_call": false, "source_file": "C:\\Users\\admin\\Herd\\CEIT-Library\\tests\\Feature\\ToastNotificationsTest.php", "source_location": "L57"}, {"caller_nid": "feature_toastnotificationstest_toastnotificationstest_success_toast_notifications_appear_after_actions", "callee": "TechnicalAdviser", "is_member_call": false, "source_file": "C:\\Users\\admin\\Herd\\CEIT-Library\\tests\\Feature\\ToastNotificationsTest.php", "source_location": "L58"}, {"caller_nid": "feature_toastnotificationstest_toastnotificationstest_success_toast_notifications_appear_after_actions", "callee": "Dean", "is_member_call": false, "source_file": "C:\\Users\\admin\\Herd\\CEIT-Library\\tests\\Feature\\ToastNotificationsTest.php", "source_location": "L60"}, {"caller_nid": "feature_toastnotificationstest_toastnotificationstest_success_toast_notifications_appear_after_actions", "callee": "call", "is_member_call": true, "source_file": "C:\\Users\\admin\\Herd\\CEIT-Library\\tests\\Feature\\ToastNotificationsTest.php", "source_location": "L64"}, {"caller_nid": "feature_toastnotificationstest_toastnotificationstest_success_toast_notifications_appear_after_actions", "callee": "assertHasNoErrors", "is_member_call": true, "source_file": "C:\\Users\\admin\\Herd\\CEIT-Library\\tests\\Feature\\ToastNotificationsTest.php", "source_location": "L65"}, {"caller_nid": "feature_toastnotificationstest_toastnotificationstest_error_toast_notifications_appear_on_failures", "callee": "create", "is_member_call": true, "source_file": "C:\\Users\\admin\\Herd\\CEIT-Library\\tests\\Feature\\ToastNotificationsTest.php", "source_location": "L74"}, {"caller_nid": "feature_toastnotificationstest_toastnotificationstest_error_toast_notifications_appear_on_failures", "callee": "User", "is_member_call": false, "source_file": "C:\\Users\\admin\\Herd\\CEIT-Library\\tests\\Feature\\ToastNotificationsTest.php", "source_location": "L74"}, {"caller_nid": "feature_toastnotificationstest_toastnotificationstest_error_toast_notifications_appear_on_failures", "callee": "actingAs", "is_member_call": true, "source_file": "C:\\Users\\admin\\Herd\\CEIT-Library\\tests\\Feature\\ToastNotificationsTest.php", "source_location": "L75"}, {"caller_nid": "feature_toastnotificationstest_toastnotificationstest_error_toast_notifications_appear_on_failures", "callee": "set", "is_member_call": true, "source_file": "C:\\Users\\admin\\Herd\\CEIT-Library\\tests\\Feature\\ToastNotificationsTest.php", "source_location": "L78"}, {"caller_nid": "feature_toastnotificationstest_toastnotificationstest_error_toast_notifications_appear_on_failures", "callee": "set", "is_member_call": true, "source_file": "C:\\Users\\admin\\Herd\\CEIT-Library\\tests\\Feature\\ToastNotificationsTest.php", "source_location": "L78"}, {"caller_nid": "feature_toastnotificationstest_toastnotificationstest_error_toast_notifications_appear_on_failures", "callee": "Volt", "is_member_call": false, "source_file": "C:\\Users\\admin\\Herd\\CEIT-Library\\tests\\Feature\\ToastNotificationsTest.php", "source_location": "L78"}, {"caller_nid": "feature_toastnotificationstest_toastnotificationstest_error_toast_notifications_appear_on_failures", "callee": "call", "is_member_call": true, "source_file": "C:\\Users\\admin\\Herd\\CEIT-Library\\tests\\Feature\\ToastNotificationsTest.php", "source_location": "L82"}, {"caller_nid": "feature_toastnotificationstest_toastnotificationstest_error_toast_notifications_appear_on_failures", "callee": "assertHasErrors", "is_member_call": true, "source_file": "C:\\Users\\admin\\Herd\\CEIT-Library\\tests\\Feature\\ToastNotificationsTest.php", "source_location": "L83"}]}