{"nodes": [{"id": "c_users_admin_herd_ceit_library_app_models_notification_php", "label": "Notification.php", "file_type": "code", "source_file": "C:\\Users\\admin\\Herd\\CEIT-Library\\app\\Models\\Notification.php", "source_location": "L1"}, {"id": "models_notification_notification", "label": "Notification", "file_type": "code", "source_file": "C:\\Users\\admin\\Herd\\CEIT-Library\\app\\Models\\Notification.php", "source_location": "L8"}, {"id": "models_notification_notification_user", "label": ".user()", "file_type": "code", "source_file": "C:\\Users\\admin\\Herd\\CEIT-Library\\app\\Models\\Notification.php", "source_location": "L27"}, {"id": "models_notification_notification_markasread", "label": ".markAsRead()", "file_type": "code", "source_file": "C:\\Users\\admin\\Herd\\CEIT-Library\\app\\Models\\Notification.php", "source_location": "L32"}, {"id": "models_notification_notification_scopeunread", "label": ".scopeUnread()", "file_type": "code", "source_file": "C:\\Users\\admin\\Herd\\CEIT-Library\\app\\Models\\Notification.php", "source_location": "L40"}, {"id": "models_notification_notification_scoperead", "label": ".scopeRead()", "file_type": "code", "source_file": "C:\\Users\\admin\\Herd\\CEIT-Library\\app\\Models\\Notification.php", "source_location": "L45"}, {"id": "models_notification_notification_scopeforuser", "label": ".scopeForUser()", "file_type": "code", "source_file": "C:\\Users\\admin\\Herd\\CEIT-Library\\app\\Models\\Notification.php", "source_location": "L50"}, {"id": "models_notification_notification_scopeoftype", "label": ".scopeOfType()", "file_type": "code", "source_file": "C:\\Users\\admin\\Herd\\CEIT-Library\\app\\Models\\Notification.php", "source_location": "L55"}], "edges": [{"source": "c_users_admin_herd_ceit_library_app_models_notification_php", "target": "model", "relation": "imports", "context": "import", "confidence": "EXTRACTED", "source_file": "C:\\Users\\admin\\Herd\\CEIT-Library\\app\\Models\\Notification.php", "source_location": "L5", "weight": 1.0}, {"source": "c_users_admin_herd_ceit_library_app_models_notification_php", "target": "belongsto", "relation": "imports", "context": "import", "confidence": "EXTRACTED", "source_file": "C:\\Users\\admin\\Herd\\CEIT-Library\\app\\Models\\Notification.php", "source_location": "L6", "weight": 1.0}, {"source": "c_users_admin_herd_ceit_library_app_models_notification_php", "target": "models_notification_notification", "relation": "contains", "confidence": "EXTRACTED", "source_file": "C:\\Users\\admin\\Herd\\CEIT-Library\\app\\Models\\Notification.php", "source_location": "L8", "weight": 1.0}, {"source": "models_notification_notification", "target": "models_notification_notification_user", "relation": "method", "confidence": "EXTRACTED", "source_file": "C:\\Users\\admin\\Herd\\CEIT-Library\\app\\Models\\Notification.php", "source_location": "L27", "weight": 1.0}, {"source": "models_notification_notification", "target": "models_notification_notification_markasread", "relation": "method", "confidence": "EXTRACTED", "source_file": "C:\\Users\\admin\\Herd\\CEIT-Library\\app\\Models\\Notification.php", "source_location": "L32", "weight": 1.0}, {"source": "models_notification_notification", "target": "models_notification_notification_scopeunread", "relation": "method", "confidence": "EXTRACTED", "source_file": "C:\\Users\\admin\\Herd\\CEIT-Library\\app\\Models\\Notification.php", "source_location": "L40", "weight": 1.0}, {"source": "models_notification_notification", "target": "models_notification_notification_scoperead", "relation": "method", "confidence": "EXTRACTED", "source_file": "C:\\Users\\admin\\Herd\\CEIT-Library\\app\\Models\\Notification.php", "source_location": "L45", "weight": 1.0}, {"source": "models_notification_notification", "target": "models_notification_notification_scopeforuser", "relation": "method", "confidence": "EXTRACTED", "source_file": "C:\\Users\\admin\\Herd\\CEIT-Library\\app\\Models\\Notification.php", "source_location": "L50", "weight": 1.0}, {"source": "models_notification_notification", "target": "models_notification_notification_scopeoftype", "relation": "method", "confidence": "EXTRACTED", "source_file": "C:\\Users\\admin\\Herd\\CEIT-Library\\app\\Models\\Notification.php", "source_location": "L55", "weight": 1.0}], "raw_calls": [{"caller_nid": "models_notification_notification_user", "callee": "belongsTo", "is_member_call": true, "source_file": "C:\\Users\\admin\\Herd\\CEIT-Library\\app\\Models\\Notification.php", "source_location": "L29"}, {"caller_nid": "models_notification_notification_markasread", "callee": "update", "is_member_call": true, "source_file": "C:\\Users\\admin\\Herd\\CEIT-Library\\app\\Models\\Notification.php", "source_location": "L34"}, {"caller_nid": "models_notification_notification_markasread", "callee": "now", "is_member_call": false, "source_file": "C:\\Users\\admin\\Herd\\CEIT-Library\\app\\Models\\Notification.php", "source_location": "L36"}, {"caller_nid": "models_notification_notification_scopeunread", "callee": "where", "is_member_call": true, "source_file": "C:\\Users\\admin\\Herd\\CEIT-Library\\app\\Models\\Notification.php", "source_location": "L42"}, {"caller_nid": "models_notification_notification_scoperead", "callee": "where", "is_member_call": true, "source_file": "C:\\Users\\admin\\Herd\\CEIT-Library\\app\\Models\\Notification.php", "source_location": "L47"}, {"caller_nid": "models_notification_notification_scopeforuser", "callee": "where", "is_member_call": true, "source_file": "C:\\Users\\admin\\Herd\\CEIT-Library\\app\\Models\\Notification.php", "source_location": "L52"}, {"caller_nid": "models_notification_notification_scopeoftype", "callee": "where", "is_member_call": true, "source_file": "C:\\Users\\admin\\Herd\\CEIT-Library\\app\\Models\\Notification.php", "source_location": "L57"}]}